{"Timestamp":"2026-03-27T21:07:48.245524300+00:00","Fase":"Accion","Contexto":"GesFer","Command":"git restore docs/diagnostics/main/execution_history.json; git restore docs/diagnostics/feat/correccion-auditorias-2026-03-23-9043078618454227804/execution_history.json 2>$null; git merge origin/main -m \"merge: sincronizar main en feat/correccion-auditorias-2026-03-23\"","Status":"Failed","ExitCode":1,"Output":"Auto-merging src/app/api/companies/[id]/route.ts CONFLICT (content): Merge conflict in src/app/api/companies/[id]/route.ts Auto-merging src/app/api/companies/route.ts CONFLICT (content): Merge conflict in src/app/api/companies/route.ts Auto-merging src/app/companies/page.tsx CONFLICT (content): Merge conflict in src/app/companies/page.tsx Auto-merging src/components/companies/company-form.tsx Automatic merge failed; fix conflicts and then commit the result."}
